LICENSE.md
MANIFEST.in
README.rst
pyproject.toml
requirements.txt
setup.py
core_module_chemical_composition_simple_app/__init__.py
core_module_chemical_composition_simple_app/urls.py
core_module_chemical_composition_simple_app/views.py
core_module_chemical_composition_simple_app.egg-info/PKG-INFO
core_module_chemical_composition_simple_app.egg-info/SOURCES.txt
core_module_chemical_composition_simple_app.egg-info/dependency_links.txt
core_module_chemical_composition_simple_app.egg-info/requires.txt
core_module_chemical_composition_simple_app.egg-info/top_level.txt
core_module_chemical_composition_simple_app/static/core_module_chemical_composition_simple_app/js/chemical_element_composition_simple.js
tests/__init__.py
tests/test_settings.py