Metadata-Version: 2.1
Name: core-module-chemical-composition-simple-app
Version: 2.19.0
Summary: Chemical composition simple module for the parser core project
Home-page: https://github.com/usnistgov/core_module_chemical_composition_simple_app
Author: NIST IT Lab
Author-email: itl_inquiries@nist.gov
License-File: LICENSE.md
